{"State":"Uttarakhand","District":"Nainital","COORD_X":79.5383866938,"COORD_Y":29.3323541139}
{"State":"Uttarakhand","District":"Dehradun","COORD_X":77.9938818769,"COORD_Y":30.4677449847}
{"State":"Uttarakhand","District":"Almora","COORD_X":79.5149316657,"COORD_Y":29.6798417861}
{"State":"Uttarakhand","District":"Champawat","COORD_X":80.0862238838,"COORD_Y":29.2929676265}
{"State":"Uttarakhand","District":"Uttarkashi","COORD_X":78.5034794742,"COORD_Y":30.9043577086}
{"State":"Uttarakhand","District":"Garhwal","COORD_X":78.7901131742,"COORD_Y":29.9336864886}
{"State":"Uttarakhand","District":"Hardwar","COORD_X":77.9798947463,"COORD_Y":29.8513636568}
{"State":"Uttarakhand","District":"Rudraprayag","COORD_X":79.0671681959,"COORD_Y":30.4765873507}
{"State":"Uttarakhand","District":"Tehri Garhwal","COORD_X":78.464403952,"COORD_Y":30.4333244467}
{"State":"Uttarakhand","District":"Bageshwar","COORD_X":79.8376106439,"COORD_Y":29.9616302263}
{"State":"Uttarakhand","District":"Pithoragarh","COORD_X":80.3724990094,"COORD_Y":30.0799947629}
{"State":"Uttarakhand","District":"Chamoli","COORD_X":79.5610128018,"COORD_Y":30.4043325929}
{"State":"Uttarakhand","District":"Udham Singh Nagar","COORD_X":79.4247058457,"COORD_Y":29.0258939533}
{"State":"Himachal Pradesh","District":"Chamba","COORD_X":76.2852097659,"COORD_Y":32.5979009688}
{"State":"Himachal Pradesh","District":"Shimla","COORD_X":77.6780931473,"COORD_Y":31.1366805822}
{"State":"Himachal Pradesh","District":"Bilaspur (Himachal Pradesh)","COORD_X":76.650640094,"COORD_Y":31.3622446672}
{"State":"Himachal Pradesh","District":"Kangra","COORD_X":76.2289804339,"COORD_Y":32.0661019961}
{"State":"Himachal Pradesh","District":"Lahul & Spiti","COORD_X":77.484150104,"COORD_Y":32.5209341922}
{"State":"Himachal Pradesh","District":"Una","COORD_X":76.2296007351,"COORD_Y":31.5669991635}
{"State":"Himachal Pradesh","District":"Solan","COORD_X":76.9423380903,"COORD_Y":30.9721375308}
{"State":"Himachal Pradesh","District":"Sirmaur","COORD_X":77.4230767302,"COORD_Y":30.6039447449}
{"State":"Himachal Pradesh","District":"Kinnaur","COORD_X":78.5913374314,"COORD_Y":31.4278515501}
{"State":"Himachal Pradesh","District":"Mandi","COORD_X":76.9454331165,"COORD_Y":31.6401492073}
{"State":"Himachal Pradesh","District":"Kullu","COORD_X":77.4126552574,"COORD_Y":31.7780480198}
{"State":"Madhya Pradesh","District":"Bhind","COORD_X":78.6418010968,"COORD_Y":26.3113864718}
{"State":"Madhya Pradesh","District":"Jhabua","COORD_X":74.7923054309,"COORD_Y":22.898345781}
{"State":"Madhya Pradesh","District":"Seoni","COORD_X":79.6359854355,"COORD_Y":22.3675393993}
{"State":"Madhya Pradesh","District":"Khandwa (East Nimar)","COORD_X":76.5346012272,"COORD_Y":22.0505663}
{"State":"Madhya Pradesh","District":"Umaria","COORD_X":80.8804667142,"COORD_Y":23.6744947616}
{"State":"Himachal Pradesh","District":"Hamirpur (Himachal Pradesh)","COORD_X":76.545699776,"COORD_Y":31.700998643}
{"State":"Jammu & Kashmir","District":"Anantnag","COORD_X":75.2611670804,"COORD_Y":33.8685983795}
{"State":"Jammu & Kashmir","District":"Baramula","COORD_X":74.3362210178,"COORD_Y":34.1117708362}
{"State":"Jammu & Kashmir","District":"Kulgam","COORD_X":74.9048864299,"COORD_Y":33.615994779}
{"State":"Jammu & Kashmir","District":"Shupiyan","COORD_X":74.8576654989,"COORD_Y":33.7112473897}
{"State":"Jammu & Kashmir","District":"Reasi","COORD_X":74.7310949357,"COORD_Y":33.1645049149}
{"State":"Jammu & Kashmir","District":"Rajouri","COORD_X":74.4472788661,"COORD_Y":33.263140648}
{"State":"Jammu & Kashmir","District":"Jammu","COORD_X":74.7551954203,"COORD_Y":32.7702564246}
{"State":"Jammu & Kashmir","District":"Srinagar","COORD_X":74.8959144225,"COORD_Y":34.073654107}
{"State":"Jammu & Kashmir","District":"Punch","COORD_X":74.3101106704,"COORD_Y":33.6167032642}
{"State":"Jammu & Kashmir","District":"Kupwara","COORD_X":74.166924006,"COORD_Y":34.4409935179}
{"State":"Jammu & Kashmir","District":"Samba","COORD_X":75.014164615,"COORD_Y":32.6170122118}
{"State":"Jammu & Kashmir","District":"Bandipore","COORD_X":74.7709181912,"COORD_Y":34.3781153989}
{"State":"Jammu & Kashmir","District":"Kathua","COORD_X":75.4288183781,"COORD_Y":32.5758174179}
{"State":"Jammu & Kashmir","District":"Kishtwar","COORD_X":76.0177279115,"COORD_Y":33.549811278}
{"State":"Gujarat","District":"Sabar Kantha","COORD_X":73.0932273304,"COORD_Y":23.6951474779}
{"State":"Gujarat","District":"Banas Kantha","COORD_X":72.0922806705,"COORD_Y":24.2246165374}
{"State":"Gujarat","District":"Surendranagar","COORD_X":71.565444352,"COORD_Y":22.7913466283}
{"State":"Gujarat","District":"Anand","COORD_X":72.7427365285,"COORD_Y":22.5139180533}
{"State":"Gujarat","District":"Narmada","COORD_X":73.6811380329,"COORD_Y":21.8073210452}
{"State":"Gujarat","District":"Amreli","COORD_X":71.3374770436,"COORD_Y":21.3564392354}
{"State":"Gujarat","District":"Dohad","COORD_X":74.0130940515,"COORD_Y":22.9175298302}
{"State":"Jammu & Kashmir","District":"Doda","COORD_X":75.6860938095,"COORD_Y":33.1126159416}
{"State":"Jammu & Kashmir","District":"Pulwama","COORD_X":74.9650606639,"COORD_Y":33.8724926367}
{"State":"Gujarat","District":"Vadodara","COORD_X":73.2777754614,"COORD_Y":22.2415915902}
{"State":"Gujarat","District":"Aravali","COORD_X":73.2201114168,"COORD_Y":23.5250010108}
{"State":"Madhya Pradesh","District":"Gwalior","COORD_X":78.1984715753,"COORD_Y":26.0536218917}
{"State":"Madhya Pradesh","District":"Damoh","COORD_X":79.4750813099,"COORD_Y":23.7801762229}
{"State":"Madhya Pradesh","District":"Dhar","COORD_X":75.1488645924,"COORD_Y":22.5797290693}
{"State":"Madhya Pradesh","District":"Katni","COORD_X":80.5018449574,"COORD_Y":23.827735361}
{"State":"Madhya Pradesh","District":"Sidhi","COORD_X":81.848677468,"COORD_Y":24.2924266931}
{"State":"Madhya Pradesh","District":"Alirajpur","COORD_X":74.4197757874,"COORD_Y":22.2344783683}
{"State":"Madhya Pradesh","District":"Singrauli","COORD_X":82.5075403207,"COORD_Y":24.3523014644}
{"State":"Madhya Pradesh","District":"Bhopal","COORD_X":77.3795470205,"COORD_Y":23.4797577449}
{"State":"Jammu & Kashmir","District":"Ramban","COORD_X":75.219590973,"COORD_Y":33.3236571747}
{"State":"Jammu & Kashmir","District":"Ganderbal","COORD_X":75.0028774035,"COORD_Y":34.2345864123}
{"State":"Jammu & Kashmir","District":"Udhampur","COORD_X":75.2733706282,"COORD_Y":32.8294971138}
{"State":"Jammu & Kashmir","District":"Badgam","COORD_X":74.7208984938,"COORD_Y":33.8914475127}
{"State":"Madhya Pradesh","District":"Rajgarh","COORD_X":76.7908052299,"COORD_Y":23.743210331}
{"State":"Madhya Pradesh","District":"Mandla","COORD_X":80.4315481916,"COORD_Y":22.6596932835}
{"State":"Madhya Pradesh","District":"Shajapur","COORD_X":76.3975887782,"COORD_Y":23.5015757035}
{"State":"Madhya Pradesh","District":"Shivpuri","COORD_X":77.7792598781,"COORD_Y":25.4021424929}
{"State":"Madhya Pradesh","District":"Datia","COORD_X":78.6171733808,"COORD_Y":25.9237460401}
{"State":"Madhya Pradesh","District":"Shahdol","COORD_X":81.4648987722,"COORD_Y":23.701670312}
{"State":"Madhya Pradesh","District":"Vidisha","COORD_X":77.8098448276,"COORD_Y":23.8109733362}
{"State":"Andhra Pradesh","District":"Prakasam","COORD_X":79.7114953119,"COORD_Y":15.6712883903}
{"State":"Andhra Pradesh","District":"Krishna","COORD_X":80.7408743705,"COORD_Y":16.6616305982}
{"State":"West Bengal","District":"Hugli","COORD_X":88.070803081,"COORD_Y":22.8675647526}
{"State":"Uttar Pradesh","District":"Ambedkar Nagar","COORD_X":82.6755922688,"COORD_Y":26.3935758084}
{"State":"Uttar Pradesh","District":"Ballia","COORD_X":84.059263125,"COORD_Y":25.8329379923}
{"State":"Uttar Pradesh","District":"Kanpur Nagar","COORD_X":80.162715854,"COORD_Y":26.4369009202}
{"State":"Uttar Pradesh","District":"Sant Ravidas Nagar (Bhadohi)","COORD_X":82.4575475769,"COORD_Y":25.3564575659}
{"State":"Daman & Diu","District":"Daman","COORD_X":72.8497527982,"COORD_Y":20.3870331075}
{"State":"Daman & Diu","District":"Diu","COORD_X":70.9422431818,"COORD_Y":20.7173251363}
{"State":"Gujarat","District":"Bhavnagar","COORD_X":71.7519605685,"COORD_Y":21.5490783273}
{"State":"Gujarat","District":"Ahmadabad","COORD_X":72.2996405265,"COORD_Y":22.7952234959}
{"State":"Gujarat","District":"Chhota Udaipur","COORD_X":73.8436649062,"COORD_Y":22.1575865547}
{"State":"Gujarat","District":"Batod","COORD_X":71.7789014396,"COORD_Y":22.055301491}
{"State":"Gujarat","District":"Rajkot","COORD_X":70.7685631925,"COORD_Y":22.1617483597}
{"State":"Gujarat","District":"Kachchh","COORD_X":70.1348318979,"COORD_Y":23.5733374001}
{"State":"Andhra Pradesh","District":"Kurnool","COORD_X":77.8701326812,"COORD_Y":15.4923142531}
{"State":"Andhra Pradesh","District":"Guntur","COORD_X":80.1408643178,"COORD_Y":16.2598712286}
{"State":"Andhra Pradesh","District":"Vizianagaram","COORD_X":83.3927600417,"COORD_Y":18.4995449814}
{"State":"Andhra Pradesh","District":"Anantapur","COORD_X":77.4522060408,"COORD_Y":14.2676601554}
{"State":"Andhra Pradesh","District":"West Godavari","COORD_X":81.3955834783,"COORD_Y":16.8581268494}
{"State":"Andhra Pradesh","District":"Kadapa","COORD_X":78.6742990749,"COORD_Y":14.5113636394}
{"State":"Kerala","District":"Kannur","COORD_X":75.5366865064,"COORD_Y":11.922267002}
{"State":"Kerala","District":"Pathanamthitta","COORD_X":76.7603297333,"COORD_Y":9.3305874702}
{"State":"Kerala","District":"Alappuzha","COORD_X":76.5443723169,"COORD_Y":9.3636067068}
{"State":"Kerala","District":"Ernakulam","COORD_X":76.6300269208,"COORD_Y":10.0627970917}
{"State":"Kerala","District":"Kollam","COORD_X":76.8381675085,"COORD_Y":8.9722242356}
{"State":"Kerala","District":"Kasaragod","COORD_X":75.1955940789,"COORD_Y":12.4230760375}
{"State":"Kerala","District":"Idukki","COORD_X":76.9259279737,"COORD_Y":9.8101893344}
{"State":"Gujarat","District":"The Dangs","COORD_X":73.6520382544,"COORD_Y":20.7949777556}
{"State":"Gujarat","District":"Mahesana","COORD_X":72.4278931258,"COORD_Y":23.5321507399}
{"State":"Gujarat","District":"Patan","COORD_X":71.6795066863,"COORD_Y":23.7576765071}
{"State":"Gujarat","District":"Bharuch","COORD_X":72.9416458408,"COORD_Y":21.7558790933}
{"State":"Gujarat","District":"Gir Somnath","COORD_X":70.6471808983,"COORD_Y":21.0072864255}
{"State":"Gujarat","District":"Junagadh","COORD_X":70.4685878644,"COORD_Y":21.2913349675}
{"State":"Gujarat","District":"Devbhumi Dwarka","COORD_X":69.5523754562,"COORD_Y":22.2276055236}
{"State":"Gujarat","District":"Navsari","COORD_X":73.0923442651,"COORD_Y":20.8438776236}
{"State":"Gujarat","District":"Surat","COORD_X":73.1420778311,"COORD_Y":21.2180404185}
{"State":"Gujarat","District":"Jamnagar","COORD_X":70.109984739,"COORD_Y":22.3859598605}
{"State":"Gujarat","District":"Tapi","COORD_X":73.7179372965,"COORD_Y":21.2518876906}
{"State":"Gujarat","District":"Kheda","COORD_X":72.9388333456,"COORD_Y":22.8133796452}
{"State":"Madhya Pradesh","District":"Betul","COORD_X":77.8959032348,"COORD_Y":22.0266948543}
{"State":"Madhya Pradesh","District":"Hoshangabad","COORD_X":78.0710672105,"COORD_Y":22.5411385662}
{"State":"Madhya Pradesh","District":"Sehore","COORD_X":77.1356016793,"COORD_Y":23.0115635424}
{"State":"Madhya Pradesh","District":"Jabalpur","COORD_X":79.9864181193,"COORD_Y":23.2098100369}
{"State":"Madhya Pradesh","District":"Narsimhapur","COORD_X":79.0881283659,"COORD_Y":22.9758525324}
{"State":"Madhya Pradesh","District":"Panna","COORD_X":80.2140577881,"COORD_Y":24.4197605365}
{"State":"Madhya Pradesh","District":"Ujjain","COORD_X":75.6934507168,"COORD_Y":23.2868015571}
{"State":"Madhya Pradesh","District":"Rewa","COORD_X":81.6241727629,"COORD_Y":24.7551654006}
{"State":"Madhya Pradesh","District":"Dindori","COORD_X":80.9809794985,"COORD_Y":22.8645729056}
{"State":"Madhya Pradesh","District":"Balaghat","COORD_X":80.4121511336,"COORD_Y":21.9321389666}
{"State":"Madhya Pradesh","District":"Barwani","COORD_X":75.0460490653,"COORD_Y":21.848792323}
{"State":"Gujarat","District":"Porbandar","COORD_X":69.8383153286,"COORD_Y":21.6820326404}
{"State":"Gujarat","District":"Valsad","COORD_X":73.043792084,"COORD_Y":20.3636611513}
{"State":"Gujarat","District":"Gandhinagar","COORD_X":72.6071371552,"COORD_Y":23.2355417153}
{"State":"Gujarat","District":"Mahisagar","COORD_X":73.6430911716,"COORD_Y":23.0970244311}
{"State":"Gujarat","District":"Morbi","COORD_X":70.94268899,"COORD_Y":22.761988857}
{"State":"Gujarat","District":"Panch Mahals","COORD_X":73.6547138957,"COORD_Y":22.7386457536}
{"State":"Kerala","District":"Kozhikode","COORD_X":75.8250130723,"COORD_Y":11.4636178664}
{"State":"Kerala","District":"Kottayam","COORD_X":76.7109613489,"COORD_Y":9.5587075301}
{"State":"Kerala","District":"Thrissur","COORD_X":76.4387868587,"COORD_Y":10.4458388962}
{"State":"Kerala","District":"Palakkad","COORD_X":76.4118381983,"COORD_Y":10.7768548441}
{"State":"Kerala","District":"Thiruvananthapuram","COORD_X":76.9452719819,"COORD_Y":8.7059766882}
{"State":"Kerala","District":"Malappuram","COORD_X":76.0906180012,"COORD_Y":11.0901858887}
{"State":"Kerala","District":"Wayanad","COORD_X":76.0120004877,"COORD_Y":11.7131010557}
{"State":"Lakshadweep","District":"Lakshadweep","COORD_X":72.7780565488,"COORD_Y":10.5170188463}
{"State":"Sikkim","District":"North Sikkim","COORD_X":88.3690900925,"COORD_Y":27.7798150616}
{"State":"Bihar","District":"Sheikhpura","COORD_X":85.8472660889,"COORD_Y":25.1231748621}
{"State":"Bihar","District":"Jehanabad","COORD_X":85.056282805,"COORD_Y":25.1718393583}
{"State":"Bihar","District":"Saharsa","COORD_X":86.5297051459,"COORD_Y":25.8468065348}
{"State":"Dadra & Nagar Haveli","District":"Dadra & Nagar Haveli","COORD_X":73.0502655363,"COORD_Y":20.2137670934}
{"State":"Madhya Pradesh","District":"Ashoknagar","COORD_X":77.829920195,"COORD_Y":24.6529340466}
{"State":"Madhya Pradesh","District":"Raisen","COORD_X":78.1385460505,"COORD_Y":23.3564425347}
{"State":"Madhya Pradesh","District":"Chhindwara","COORD_X":78.8197920777,"COORD_Y":22.3137627851}
{"State":"Bihar","District":"Patna","COORD_X":85.30336347,"COORD_Y":25.4245661128}
{"State":"Madhya Pradesh","District":"Satna","COORD_X":80.7469114992,"COORD_Y":24.4647740141}
{"State":"Madhya Pradesh","District":"Chhatarpur","COORD_X":79.5647010327,"COORD_Y":24.6422495591}
{"State":"Madhya Pradesh","District":"Indore","COORD_X":75.8117371414,"COORD_Y":22.6918447692}
{"State":"Madhya Pradesh","District":"Ratlam","COORD_X":75.1888791405,"COORD_Y":23.4242272568}
{"State":"Madhya Pradesh","District":"Harda","COORD_X":77.1353048655,"COORD_Y":22.2101870556}
{"State":"Madhya Pradesh","District":"Sagar","COORD_X":78.7971322651,"COORD_Y":23.8097106559}
{"State":"Madhya Pradesh","District":"Neemuch","COORD_X":75.1768081027,"COORD_Y":24.5786949418}
{"State":"Madhya Pradesh","District":"Tikamgarh","COORD_X":78.8949371676,"COORD_Y":25.2064325934}
{"State":"Madhya Pradesh","District":"Guna","COORD_X":77.3038540482,"COORD_Y":24.3874175598}
{"State":"Madhya Pradesh","District":"Dewas","COORD_X":76.4465354587,"COORD_Y":22.8018889566}
{"State":"Madhya Pradesh","District":"Mandsaur","COORD_X":75.3217203727,"COORD_Y":24.2278812445}
{"State":"Madhya Pradesh","District":"Khargone (West Nimar)","COORD_X":75.8028824676,"COORD_Y":22.0562357719}
{"State":"Madhya Pradesh","District":"Sheopur","COORD_X":77.3078517534,"COORD_Y":25.8137349159}
{"State":"Madhya Pradesh","District":"Morena","COORD_X":77.952122516,"COORD_Y":26.321340062}
{"State":"Madhya Pradesh","District":"Burhanpur","COORD_X":76.3023745073,"COORD_Y":21.3944963025}
{"State":"Madhya Pradesh","District":"Anuppur","COORD_X":81.7074940674,"COORD_Y":23.0805373638}
{"State":"Andhra Pradesh","District":"East Godavari","COORD_X":82.0290952585,"COORD_Y":17.1328224383}
{"State":"Andhra Pradesh","District":"Visakhapatnam","COORD_X":82.8000275567,"COORD_Y":17.9778081429}
{"State":"Andhra Pradesh","District":"Sri Potti Sriramulu Nellore","COORD_X":79.7416643656,"COORD_Y":14.2897134894}
{"State":"Andhra Pradesh","District":"Chittoor","COORD_X":79.009771642,"COORD_Y":13.3642304714}
{"State":"Andhra Pradesh","District":"Srikakulam","COORD_X":84.0765589112,"COORD_Y":18.7455918735}
{"State":"Sikkim","District":"East Sikkim","COORD_X":88.6689713235,"COORD_Y":27.2767367402}
{"State":"West Bengal","District":"Nadia","COORD_X":88.5699117555,"COORD_Y":23.5509556905}
{"State":"West Bengal","District":"Dakshin Dinajpur","COORD_X":88.6757452549,"COORD_Y":25.3497969056}
{"State":"Sikkim","District":"South Sikkim","COORD_X":88.3909384248,"COORD_Y":27.2302694867}
{"State":"West Bengal","District":"Murshidabad","COORD_X":88.123389477,"COORD_Y":24.1776285248}
{"State":"West Bengal","District":"Barddhaman","COORD_X":87.7278448244,"COORD_Y":23.4819192626}
{"State":"West Bengal","District":"Bankura","COORD_X":87.1251577093,"COORD_Y":23.1011128634}
{"State":"West Bengal","District":"Puruliya","COORD_X":86.4055197041,"COORD_Y":23.2285083246}
{"State":"West Bengal","District":"Koch Bihar","COORD_X":89.3132201072,"COORD_Y":26.2501232785}
{"State":"West Bengal","District":"Paschim Medinipur","COORD_X":87.2524939894,"COORD_Y":22.3542305835}
{"State":"Sikkim","District":"West Sikkim","COORD_X":88.1184332114,"COORD_Y":27.3703915529}
{"State":"West Bengal","District":"Kolkata","COORD_X":88.3626539616,"COORD_Y":22.5624854276}
{"State":"West Bengal","District":"Maldah","COORD_X":88.2319919779,"COORD_Y":25.0608657508}
{"State":"West Bengal","District":"South Twenty Four Parganas","COORD_X":88.5511889654,"COORD_Y":22.0870967661}
{"State":"West Bengal","District":"Darjiling","COORD_X":88.2479398583,"COORD_Y":26.890652672}
{"State":"West Bengal","District":"Jalpaiguri","COORD_X":88.9811356719,"COORD_Y":26.5876179664}
{"State":"West Bengal","District":"Uttar Dinajpur","COORD_X":88.2238605042,"COORD_Y":25.9604141577}
{"State":"West Bengal","District":"Purba Medinipur","COORD_X":87.6460919777,"COORD_Y":22.0875644532}
{"State":"West Bengal","District":"Haora","COORD_X":88.1054622799,"COORD_Y":22.57576875}
{"State":"West Bengal","District":"North Twenty Four Parganas","COORD_X":88.7127160909,"COORD_Y":22.7956749859}
{"State":"West Bengal","District":"Birbhum","COORD_X":87.6267888367,"COORD_Y":24.0131564114}
{"State":"Jharkhand","District":"Jamtara","COORD_X":86.9492608786,"COORD_Y":23.966150689}
{"State":"Jharkhand","District":"Saraikela-Kharsawan","COORD_X":85.9605296397,"COORD_Y":22.819296592}
{"State":"Jharkhand","District":"Simdega","COORD_X":84.5998441075,"COORD_Y":22.5815970191}
{"State":"Jharkhand","District":"Latehar","COORD_X":84.4734663632,"COORD_Y":23.745688741}
{"State":"Jharkhand","District":"Khunti","COORD_X":85.329819845,"COORD_Y":23.0427917178}
{"State":"Jharkhand","District":"Pashchimi Singhbhum","COORD_X":85.5270194374,"COORD_Y":22.4151895106}
{"State":"Jharkhand","District":"Hazaribagh","COORD_X":85.4339057777,"COORD_Y":24.0660216364}
{"State":"Jharkhand","District":"Chatra","COORD_X":84.8752783078,"COORD_Y":24.1459979422}
{"State":"Jharkhand","District":"Purbi Singhbhum","COORD_X":86.4435626871,"COORD_Y":22.6333223808}
{"State":"Jharkhand","District":"Kodarma","COORD_X":85.6018179768,"COORD_Y":24.4698852934}
{"State":"Jharkhand","District":"Giridih","COORD_X":86.0901010447,"COORD_Y":24.3320511175}
{"State":"Jharkhand","District":"Bokaro","COORD_X":85.9703262889,"COORD_Y":23.7055986778}
{"State":"Jharkhand","District":"Deoghar","COORD_X":86.7821181268,"COORD_Y":24.3173562176}
{"State":"Jharkhand","District":"Gumla","COORD_X":84.4783410349,"COORD_Y":23.0863557697}
{"State":"Jharkhand","District":"Ramgarh","COORD_X":85.5494196944,"COORD_Y":23.6413361675}
{"State":"Jharkhand","District":"Garhwa","COORD_X":83.6588785658,"COORD_Y":24.0966138527}
{"State":"Jharkhand","District":"Ranchi","COORD_X":85.3622272877,"COORD_Y":23.2307980737}
{"State":"Jharkhand","District":"Pakur","COORD_X":87.6822541325,"COORD_Y":24.5856966119}
{"State":"Bihar","District":"Gopalganj","COORD_X":84.4461859441,"COORD_Y":26.3737530734}
{"State":"Bihar","District":"Vaishali","COORD_X":85.3702803045,"COORD_Y":25.833842546}
{"State":"Bihar","District":"Siwan","COORD_X":84.4217812118,"COORD_Y":26.1787662737}
{"State":"Bihar","District":"Sheohar","COORD_X":85.3328097169,"COORD_Y":26.4825357533}
{"State":"Bihar","District":"Buxar","COORD_X":84.0357294683,"COORD_Y":25.4165691876}
{"State":"Bihar","District":"Madhubani","COORD_X":86.2061526298,"COORD_Y":26.3887006548}
{"State":"Bihar","District":"Supaul","COORD_X":86.7932303101,"COORD_Y":26.2488598198}
{"State":"Bihar","District":"Bhojpur","COORD_X":84.5320373625,"COORD_Y":25.5005796117}
{"State":"Bihar","District":"Darbhanga","COORD_X":86.0457971208,"COORD_Y":26.0729712568}
{"State":"Bihar","District":"Samastipur","COORD_X":85.9314652055,"COORD_Y":25.7672360924}
{"State":"Bihar","District":"Kaimur (Bhabua)","COORD_X":83.6975952803,"COORD_Y":25.095862656}
{"State":"Bihar","District":"Rohtas","COORD_X":83.9691755048,"COORD_Y":25.0631974217}
{"State":"Bihar","District":"Khagaria","COORD_X":86.5443203782,"COORD_Y":25.5326564123}
{"State":"Jharkhand","District":"Lohardaga","COORD_X":84.7171532366,"COORD_Y":23.5119950687}
{"State":"Jharkhand","District":"Sahibganj","COORD_X":87.6407176709,"COORD_Y":24.9072474455}
{"State":"Jharkhand","District":"Godda","COORD_X":87.3395865152,"COORD_Y":24.8702040341}
{"State":"Jharkhand","District":"Palamu","COORD_X":84.2515000357,"COORD_Y":24.1773410957}
{"State":"Bihar","District":"Arwal","COORD_X":84.7454547102,"COORD_Y":25.16661453}
{"State":"Bihar","District":"Bhagalpur","COORD_X":86.9767075168,"COORD_Y":25.2593685722}
{"State":"Bihar","District":"Purnia","COORD_X":87.4293071848,"COORD_Y":25.8161133262}
{"State":"Bihar","District":"Madhepura","COORD_X":86.9020858386,"COORD_Y":25.7846689301}
{"State":"Bihar","District":"Munger","COORD_X":86.5302449947,"COORD_Y":25.1884485109}
{"State":"Bihar","District":"Sitamarhi","COORD_X":85.5151021631,"COORD_Y":26.5370882894}
{"State":"Bihar","District":"Purba Champaran","COORD_X":85.0130757286,"COORD_Y":26.626791931}
{"State":"Bihar","District":"Lakhisarai","COORD_X":86.0660530539,"COORD_Y":25.1387467018}
{"State":"Bihar","District":"Jamui","COORD_X":86.2341545509,"COORD_Y":24.8402816516}
{"State":"Bihar","District":"Begusarai","COORD_X":86.1204911808,"COORD_Y":25.5571580067}
{"State":"Bihar","District":"Nalanda","COORD_X":85.4760413709,"COORD_Y":25.2254966496}
{"State":"Bihar","District":"Katihar","COORD_X":87.6036309088,"COORD_Y":25.6218385825}
{"State":"NCT of Delhi","District":"West Delhi","COORD_X":77.0863883825,"COORD_Y":28.6418988143}
{"State":"Haryana","District":"Mewat","COORD_X":77.0614746828,"COORD_Y":27.9523167224}
{"State":"Haryana","District":"Jhajjar","COORD_X":76.6751089979,"COORD_Y":28.6142320917}
{"State":"Haryana","District":"Bhiwani","COORD_X":75.9420632354,"COORD_Y":28.73291034}
{"State":"Haryana","District":"Kaithal","COORD_X":76.4383652242,"COORD_Y":29.8191559073}
{"State":"Uttar Pradesh","District":"Siddharthnagar","COORD_X":82.8810985692,"COORD_Y":27.2715182471}
{"State":"Uttar Pradesh","District":"Sant Kabir Nagar","COORD_X":82.9991074663,"COORD_Y":26.79289325}
{"State":"Jharkhand","District":"Dhanbad","COORD_X":86.4225327273,"COORD_Y":23.8462726274}
{"State":"Jharkhand","District":"Dumka","COORD_X":87.2856535323,"COORD_Y":24.2927566667}
{"State":"Bihar","District":"Kishanganj","COORD_X":87.8755664962,"COORD_Y":26.296493352}
{"State":"Bihar","District":"Gaya","COORD_X":84.925673059,"COORD_Y":24.7863098007}
{"State":"Bihar","District":"Banka","COORD_X":86.7712105851,"COORD_Y":24.9091100774}
{"State":"Bihar","District":"Aurangabad (Bihar)","COORD_X":84.5408676603,"COORD_Y":24.8131148961}
{"State":"Bihar","District":"Nawada","COORD_X":85.6207103779,"COORD_Y":24.9034833802}
{"State":"Bihar","District":"Araria","COORD_X":87.305619121,"COORD_Y":26.1751575534}
{"State":"Bihar","District":"Pashchim Champaran","COORD_X":84.3871745845,"COORD_Y":27.1651823801}
{"State":"Bihar","District":"Muzaffarpur","COORD_X":85.3414406112,"COORD_Y":26.1699233508}
{"State":"Bihar","District":"Saran","COORD_X":84.83834293,"COORD_Y":25.9150099166}
{"State":"NCT of Delhi","District":"New Delhi","COORD_X":77.2074379917,"COORD_Y":28.6135970701}
{"State":"Haryana","District":"Sonipat","COORD_X":76.8967534978,"COORD_Y":29.0233064678}
{"State":"Haryana","District":"Karnal","COORD_X":76.929615577,"COORD_Y":29.7198798385}
{"State":"Haryana","District":"Kurukshetra","COORD_X":76.7902176338,"COORD_Y":30.0463398611}
{"State":"Haryana","District":"Jind","COORD_X":76.3090994746,"COORD_Y":29.4191646785}
{"State":"Haryana","District":"Panipat","COORD_X":76.942480127,"COORD_Y":29.3415704252}
{"State":"Haryana","District":"Mahendragarh","COORD_X":76.1157363286,"COORD_Y":28.122581325}
{"State":"Haryana","District":"Fatehabad","COORD_X":75.5676873179,"COORD_Y":29.4997619573}
{"State":"Punjab","District":"Shahid Bhagat Singh Nagar","COORD_X":76.1294576999,"COORD_Y":31.1297061919}
{"State":"Karnataka","District":"Mandya","COORD_X":76.8055735241,"COORD_Y":12.5755362111}
{"State":"Karnataka","District":"Mysore","COORD_X":76.5602210434,"COORD_Y":12.2746242309}
{"State":"Karnataka","District":"Chikkaballapura","COORD_X":77.8891187582,"COORD_Y":13.5184175817}
{"State":"Karnataka","District":"Yadgir","COORD_X":76.9586960281,"COORD_Y":16.7180180554}
{"State":"Karnataka","District":"Chikmagalur","COORD_X":75.7566301844,"COORD_Y":13.433246648}
{"State":"Karnataka","District":"Chitradurga","COORD_X":76.5621785475,"COORD_Y":14.2474624556}
{"State":"Karnataka","District":"Haveri","COORD_X":75.4303311538,"COORD_Y":14.7026053272}
{"State":"Karnataka","District":"Dakshina Kannada","COORD_X":75.2358742877,"COORD_Y":12.7956414107}
{"State":"Karnataka","District":"Raichur","COORD_X":76.8842877241,"COORD_Y":16.07431898}
{"State":"Karnataka","District":"Kolar","COORD_X":78.1967142942,"COORD_Y":13.1660259438}
{"State":"Karnataka","District":"Bijapur (Karnataka)","COORD_X":75.9657533988,"COORD_Y":16.8597386932}
{"State":"Karnataka","District":"Uttara Kannada","COORD_X":74.4601721918,"COORD_Y":14.5680698463}
{"State":"Karnataka","District":"Davanagere","COORD_X":75.9277775123,"COORD_Y":14.4036698418}
{"State":"Karnataka","District":"Dharwad","COORD_X":75.1549366919,"COORD_Y":15.3507748675}
{"State":"Karnataka","District":"Bidar","COORD_X":77.2060545315,"COORD_Y":17.9359715797}
{"State":"Karnataka","District":"Chamarajanagar","COORD_X":77.0961459068,"COORD_Y":11.990064311}
{"State":"Karnataka","District":"Gulbarga","COORD_X":76.8864532871,"COORD_Y":17.1358266133}
{"State":"Karnataka","District":"Gadag","COORD_X":75.6512365542,"COORD_Y":15.4984868193}
{"State":"Karnataka","District":"Udupi","COORD_X":74.8008507277,"COORD_Y":13.5356843173}
{"State":"Karnataka","District":"Bagalkot","COORD_X":75.6285432758,"COORD_Y":16.1947799605}
{"State":"Karnataka","District":"Hassan","COORD_X":76.1138292803,"COORD_Y":12.9476312738}
{"State":"Karnataka","District":"Shimoga","COORD_X":75.2209699003,"COORD_Y":14.1731353128}
{"State":"Karnataka","District":"Bellary","COORD_X":76.4719793727,"COORD_Y":15.103931155}
{"State":"Karnataka","District":"Kodagu","COORD_X":75.7727152816,"COORD_Y":12.337026751}
{"State":"NCT of Delhi","District":"East Delhi","COORD_X":77.2945434159,"COORD_Y":28.6359800261}
{"State":"NCT of Delhi","District":"South Delhi","COORD_X":77.2252873535,"COORD_Y":28.5108105182}
{"State":"NCT of Delhi","District":"North West Delhi","COORD_X":77.1058139589,"COORD_Y":28.7771828299}
{"State":"NCT of Delhi","District":"South West Delhi","COORD_X":77.0476804666,"COORD_Y":28.5769760773}
{"State":"Haryana","District":"Faridabad","COORD_X":77.3466844007,"COORD_Y":28.3859132808}
{"State":"Haryana","District":"Sirsa","COORD_X":74.9047026987,"COORD_Y":29.532594787}
{"State":"Haryana","District":"Hisar","COORD_X":75.8040203852,"COORD_Y":29.2197483333}
{"State":"Karnataka","District":"Bangalore Rural","COORD_X":77.5487576874,"COORD_Y":13.1838235501}
{"State":"Karnataka","District":"Tumkur","COORD_X":77.0567121948,"COORD_Y":13.6459309247}
{"State":"Karnataka","District":"Belgaum","COORD_X":74.7765607134,"COORD_Y":16.2089313674}
{"State":"Karnataka","District":"Koppal","COORD_X":76.2290409222,"COORD_Y":15.6201604611}
{"State":"Karnataka","District":"Bangalore","COORD_X":77.5782478852,"COORD_Y":12.9545827768}
{"State":"Karnataka","District":"Ramanagara","COORD_X":77.3132330758,"COORD_Y":12.7981227778}
{"State":"Maharashtra","District":"Washim","COORD_X":77.2495529103,"COORD_Y":20.2724885537}
{"State":"Maharashtra","District":"Ahmadnagar","COORD_X":74.7385767633,"COORD_Y":19.178211015}
{"State":"Maharashtra","District":"Latur","COORD_X":76.7514644678,"COORD_Y":18.3580003148}
{"State":"Maharashtra","District":"Solapur","COORD_X":75.3659447544,"COORD_Y":17.8141647926}
{"State":"Maharashtra","District":"Nashik","COORD_X":74.0227767138,"COORD_Y":20.2326904534}
{"State":"Maharashtra","District":"Osmanabad","COORD_X":76.0299564282,"COORD_Y":18.1905356282}
{"State":"Maharashtra","District":"Sindhudurg","COORD_X":73.6286760896,"COORD_Y":16.1201663161}
{"State":"Maharashtra","District":"Kolhapur","COORD_X":74.1798535101,"COORD_Y":16.5044308}
{"State":"Maharashtra","District":"Chandrapur","COORD_X":79.3998047475,"COORD_Y":20.1292531796}
{"State":"Maharashtra","District":"Akola","COORD_X":77.0610017971,"COORD_Y":20.7767798817}
{"State":"Maharashtra","District":"Parbhani","COORD_X":76.725476329,"COORD_Y":19.3263800522}
{"State":"Maharashtra","District":"Yavatmal","COORD_X":78.1149827004,"COORD_Y":20.02919375}
{"State":"Maharashtra","District":"Nanded","COORD_X":77.6822504557,"COORD_Y":19.2124666492}
{"State":"Maharashtra","District":"Dhule","COORD_X":74.6529280932,"COORD_Y":21.1824857822}
{"State":"Maharashtra","District":"Satara","COORD_X":74.2178921635,"COORD_Y":17.7785611951}
{"State":"Maharashtra","District":"Sangli","COORD_X":74.7275843021,"COORD_Y":17.1287966049}
{"State":"Maharashtra","District":"Hingoli","COORD_X":77.0564504885,"COORD_Y":19.6514618481}
{"State":"Maharashtra","District":"Pune","COORD_X":74.2501998732,"COORD_Y":18.4037901721}
{"State":"NCT of Delhi","District":"Central Delhi","COORD_X":77.2124159742,"COORD_Y":28.6471643703}
{"State":"Haryana","District":"Rewari","COORD_X":76.5495982355,"COORD_Y":28.2289095237}
{"State":"Haryana","District":"Rohtak","COORD_X":76.5270172625,"COORD_Y":28.9000641063}
{"State":"Haryana","District":"Ambala","COORD_X":76.9494887716,"COORD_Y":30.303837592}
{"State":"Chandigarh","District":"Chandigarh","COORD_X":76.7846566667,"COORD_Y":30.7243610853}
{"State":"Maharashtra","District":"Gondiya","COORD_X":80.2773664657,"COORD_Y":21.2086209618}
{"State":"Maharashtra","District":"Amravati","COORD_X":77.7089361616,"COORD_Y":21.2033437139}
{"State":"Maharashtra","District":"Nandurbar","COORD_X":74.1737032308,"COORD_Y":21.5530412449}
{"State":"Maharashtra","District":"Ratnagiri","COORD_X":73.3315882576,"COORD_Y":17.260886038}
{"State":"Maharashtra","District":"Wardha","COORD_X":78.5161833498,"COORD_Y":20.8033952814}
{"State":"Maharashtra","District":"Aurangabad (Maharashtra)","COORD_X":75.2519204338,"COORD_Y":19.993536449}
{"State":"Maharashtra","District":"Buldana","COORD_X":76.4254704474,"COORD_Y":20.5659349261}
{"State":"Maharashtra","District":"Gadchiroli","COORD_X":80.2423795095,"COORD_Y":19.9178861483}
{"State":"Maharashtra","District":"Jalgaon","COORD_X":75.4940880103,"COORD_Y":20.9288558155}
{"State":"Maharashtra","District":"Raigarh (Maharashtra)","COORD_X":73.1376411659,"COORD_Y":18.4945820592}
{"State":"Maharashtra","District":"Bhandara","COORD_X":79.7487883936,"COORD_Y":21.1297118613}
{"State":"Maharashtra","District":"Bid","COORD_X":75.7358159395,"COORD_Y":18.9807831175}
{"State":"Maharashtra","District":"Jalna","COORD_X":75.9952022306,"COORD_Y":19.8832655153}
{"State":"Maharashtra","District":"Thane","COORD_X":73.2260045285,"COORD_Y":19.3530358245}
{"State":"Maharashtra","District":"Palghar","COORD_X":72.9575657505,"COORD_Y":19.7381290397}
{"State":"Uttar Pradesh","District":"Varanasi","COORD_X":82.8862863216,"COORD_Y":25.3720210204}
{"State":"NCT of Delhi","District":"North East Delhi","COORD_X":77.2738848264,"COORD_Y":28.7074124074}
{"State":"Punjab","District":"Patiala","COORD_X":76.3090915346,"COORD_Y":30.2601075402}
{"State":"Punjab","District":"Tarn Taran","COORD_X":74.6845289304,"COORD_Y":31.329105278}
{"State":"Punjab","District":"Kapurthala","COORD_X":75.4858676486,"COORD_Y":31.3348214987}
{"State":"Punjab","District":"Fatehgarh Sahib","COORD_X":76.37069553,"COORD_Y":30.6425225305}
{"State":"Punjab","District":"Sangrur","COORD_X":75.9041709049,"COORD_Y":30.1564272584}
{"State":"Puducherry","District":"Yanam","COORD_X":82.2801591072,"COORD_Y":16.6939524405}
{"State":"Manipur","District":"Tamenglong","COORD_X":93.5298469836,"COORD_Y":24.9849964143}
{"State":"Uttar Pradesh","District":"Bara Banki","COORD_X":81.32824605,"COORD_Y":26.9248599622}
{"State":"Uttar Pradesh","District":"Mahoba","COORD_X":79.6714631061,"COORD_Y":25.2680569675}
{"State":"Uttar Pradesh","District":"Mahrajganj","COORD_X":83.4682559003,"COORD_Y":27.2430374437}
{"State":"Uttar Pradesh","District":"Mirzapur","COORD_X":82.5243826581,"COORD_Y":24.9307782968}
{"State":"Uttar Pradesh","District":"Kushinagar","COORD_X":83.9282427541,"COORD_Y":26.8606333882}
{"State":"NCT of Delhi","District":"North Delhi","COORD_X":77.198343908,"COORD_Y":28.7101858412}
{"State":"Haryana","District":"Gurgaon","COORD_X":76.9386805022,"COORD_Y":28.3849429686}
{"State":"Haryana","District":"Yamunanagar","COORD_X":77.2601389104,"COORD_Y":30.2645339552}
{"State":"Haryana","District":"Palwal","COORD_X":77.4120988097,"COORD_Y":28.0952894826}
{"State":"Haryana","District":"Panchkula","COORD_X":76.9698808976,"COORD_Y":30.6950508675}
{"State":"Mizoram","District":"Mamit","COORD_X":92.4111966424,"COORD_Y":23.6654012405}
{"State":"Manipur","District":"Chandel","COORD_X":94.0310585039,"COORD_Y":24.2827513358}
{"State":"Uttar Pradesh","District":"Deoria","COORD_X":83.8346964278,"COORD_Y":26.4492374132}
{"State":"Uttar Pradesh","District":"Unnao","COORD_X":80.6011721556,"COORD_Y":26.6383988847}
{"State":"Uttar Pradesh","District":"Fatehpur","COORD_X":80.8417409973,"COORD_Y":25.862794057}
{"State":"Uttar Pradesh","District":"Mau","COORD_X":83.5073134383,"COORD_Y":25.9924650484}
{"State":"Uttar Pradesh","District":"Rae Bareli","COORD_X":81.2467063971,"COORD_Y":26.2448892354}
{"State":"Uttar Pradesh","District":"Amethi","COORD_X":81.6350433723,"COORD_Y":26.3396017754}
{"State":"Uttar Pradesh","District":"Ghaziabad","COORD_X":77.4816561369,"COORD_Y":28.7185481077}
{"State":"Uttar Pradesh","District":"Muzaffarnagar","COORD_X":77.7239433474,"COORD_Y":29.449277185}
{"State":"Uttar Pradesh","District":"Gautam Buddha Nagar","COORD_X":77.4902420542,"COORD_Y":28.3797591771}
{"State":"Uttar Pradesh","District":"Saharanpur","COORD_X":77.5963981774,"COORD_Y":29.9817197285}
{"State":"Uttar Pradesh","District":"Etawah","COORD_X":79.0864936515,"COORD_Y":26.7403583569}
{"State":"Uttar Pradesh","District":"Agra","COORD_X":78.0866020726,"COORD_Y":27.0573965565}
{"State":"Tamil Nadu","District":"Cuddalore","COORD_X":79.4695028905,"COORD_Y":11.5966119117}
{"State":"Punjab","District":"Pathankot","COORD_X":75.5599182801,"COORD_Y":32.2483230733}
{"State":"Punjab","District":"Gurdaspur","COORD_X":75.2637859417,"COORD_Y":31.9780293347}
{"State":"Punjab","District":"Mansa","COORD_X":75.436636199,"COORD_Y":29.8874526465}
{"State":"Punjab","District":"Amritsar","COORD_X":74.7783372631,"COORD_Y":31.6936343975}
{"State":"Nagaland","District":"Kohima","COORD_X":94.1562181805,"COORD_Y":25.8088361135}
{"State":"Nagaland","District":"Wokha","COORD_X":94.3026709377,"COORD_Y":26.2030076031}
{"State":"Nagaland","District":"Zunheboto","COORD_X":94.4705997755,"COORD_Y":25.9989445081}
{"State":"Nagaland","District":"Kiphire","COORD_X":94.7841267531,"COORD_Y":25.8594300943}
{"State":"Punjab","District":"Faridkot","COORD_X":74.8014561051,"COORD_Y":30.5895782998}
{"State":"Punjab","District":"Ludhiana","COORD_X":75.8977326938,"COORD_Y":30.7851890574}
{"State":"Punjab","District":"Bathinda","COORD_X":75.0867694519,"COORD_Y":30.1684795111}
{"State":"Punjab","District":"Jalandhar","COORD_X":75.5326783455,"COORD_Y":31.2427121152}
{"State":"Punjab","District":"Moga","COORD_X":75.175976293,"COORD_Y":30.8218075661}
{"State":"Punjab","District":"Hoshiarpur","COORD_X":75.8765479953,"COORD_Y":31.6268794071}
{"State":"Nagaland","District":"Dimapur","COORD_X":93.8072859275,"COORD_Y":25.7821325184}
{"State":"Nagaland","District":"Peren","COORD_X":93.696847137,"COORD_Y":25.5579681555}
{"State":"Arunachal Pradesh","District":"Lohit","COORD_X":96.2555968885,"COORD_Y":27.8820314181}
{"State":"Arunachal Pradesh","District":"West Siang","COORD_X":94.5714587398,"COORD_Y":28.2131746217}
{"State":"Arunachal Pradesh","District":"Upper Subansiri","COORD_X":94.0321786751,"COORD_Y":28.1839644682}
{"State":"Arunachal Pradesh","District":"Changlang","COORD_X":96.296332644,"COORD_Y":27.3256977574}
{"State":"Arunachal Pradesh","District":"Tirap","COORD_X":95.3709506077,"COORD_Y":26.9192361648}
{"State":"Arunachal Pradesh","District":"Lower Subansiri","COORD_X":93.9053969481,"COORD_Y":27.6548586999}
{"State":"Arunachal Pradesh","District":"East Kameng","COORD_X":93.0092277101,"COORD_Y":27.4289394116}
{"State":"Arunachal Pradesh","District":"Upper Siang","COORD_X":95.0384564862,"COORD_Y":28.6568892345}
{"State":"Arunachal Pradesh","District":"Anjaw","COORD_X":96.780100528,"COORD_Y":28.0366850454}
{"State":"Arunachal Pradesh","District":"East Siang","COORD_X":95.0983436336,"COORD_Y":28.2046661055}
{"State":"Arunachal Pradesh","District":"Dibang Valley","COORD_X":95.8074584871,"COORD_Y":28.7459424969}
{"State":"Arunachal Pradesh","District":"Kurung Kumey","COORD_X":93.4927196711,"COORD_Y":27.9277310072}
{"State":"Arunachal Pradesh","District":"West Kameng","COORD_X":92.4606944969,"COORD_Y":27.3303913727}
{"State":"Arunachal Pradesh","District":"Lower Dibang Valley","COORD_X":95.7873277688,"COORD_Y":28.2955358702}
{"State":"Arunachal Pradesh","District":"Tawang","COORD_X":91.9423431128,"COORD_Y":27.6316605113}
{"State":"Arunachal Pradesh","District":"Papum Pare","COORD_X":93.5581842857,"COORD_Y":27.3681348836}
{"State":"Assam","District":"Goalpara","COORD_X":90.6310096006,"COORD_Y":26.0197187352}
{"State":"Assam","District":"Baksa","COORD_X":91.3832676553,"COORD_Y":26.5974143866}
{"State":"Assam","District":"Nagaon","COORD_X":92.8608649666,"COORD_Y":26.2539690685}
{"State":"Tamil Nadu","District":"Pudukkottai","COORD_X":78.8608619643,"COORD_Y":10.3609697271}
{"State":"Tamil Nadu","District":"Vellore","COORD_X":79.1185039696,"COORD_Y":12.804255216}
{"State":"Uttar Pradesh","District":"Chandauli","COORD_X":83.2509231036,"COORD_Y":25.1437455181}
{"State":"Punjab","District":"Muktsar","COORD_X":74.5354616871,"COORD_Y":30.3116306409}
{"State":"Punjab","District":"Rupnagar","COORD_X":76.4857163236,"COORD_Y":31.0600222118}
{"State":"Punjab","District":"Firozpur","COORD_X":74.6523215636,"COORD_Y":30.9522435412}
{"State":"Punjab","District":"Fazilka","COORD_X":74.1455073824,"COORD_Y":30.4420544835}
{"State":"Tripura","District":"West Tripura","COORD_X":91.3900908712,"COORD_Y":23.9411907944}
{"State":"Punjab","District":"Barnala","COORD_X":75.5246837466,"COORD_Y":30.4208544246}
{"State":"Punjab","District":"Sahibzada Ajit Singh Nagar","COORD_X":76.7562316862,"COORD_Y":30.6834388321}
{"State":"Maharashtra","District":"Mumbai","COORD_X":72.8364346812,"COORD_Y":18.9573318579}
{"State":"Mizoram","District":"Lunglei","COORD_X":92.6050686988,"COORD_Y":22.9673576164}
{"State":"Mizoram","District":"Kolasib","COORD_X":92.7186467933,"COORD_Y":24.1639504592}
{"State":"Mizoram","District":"Lawngtlai","COORD_X":92.6820782993,"COORD_Y":22.4364481205}
{"State":"Mizoram","District":"Saiha","COORD_X":92.9964235585,"COORD_Y":22.282671157}
{"State":"Mizoram","District":"Champhai","COORD_X":93.2259519491,"COORD_Y":23.5522527409}
{"State":"Tripura","District":"Dhalai","COORD_X":91.880919539,"COORD_Y":23.8600520191}
{"State":"Tripura","District":"Unokoti","COORD_X":91.9761212531,"COORD_Y":24.2459040059}
{"State":"Tripura","District":"North Tripura","COORD_X":92.1974673632,"COORD_Y":24.2131327192}
{"State":"Tripura","District":"Gomati","COORD_X":91.7297892711,"COORD_Y":23.3622653797}
{"State":"Tripura","District":"South Tripura","COORD_X":91.582229885,"COORD_Y":23.1301510681}
{"State":"Meghalaya","District":"South Garo Hills","COORD_X":90.6815269587,"COORD_Y":25.2316267481}
{"State":"Meghalaya","District":"Ribhoi","COORD_X":91.8072653698,"COORD_Y":25.8314792429}
{"State":"Meghalaya","District":"East Khasi Hills","COORD_X":91.7624123375,"COORD_Y":25.3301481507}
{"State":"Meghalaya","District":"West Khasi Hills","COORD_X":91.2775023683,"COORD_Y":25.5898969122}
{"State":"Meghalaya","District":"South West Khasi Hills","COORD_X":91.1972703129,"COORD_Y":25.2625059074}
{"State":"Meghalaya","District":"West Garo Hills","COORD_X":90.1847715874,"COORD_Y":25.5087555022}
{"State":"Uttar Pradesh","District":"Jhansi","COORD_X":78.8911329246,"COORD_Y":25.4301336443}
{"State":"Uttar Pradesh","District":"Banda","COORD_X":80.4673553952,"COORD_Y":25.2315644671}
{"State":"Uttar Pradesh","District":"Sonbhadra","COORD_X":82.9756266342,"COORD_Y":24.5002372072}
{"State":"Uttar Pradesh","District":"Lalitpur","COORD_X":78.6561146587,"COORD_Y":24.6984879476}
{"State":"Uttar Pradesh","District":"Ghazipur","COORD_X":83.5509838017,"COORD_Y":25.6260772684}
{"State":"Tamil Nadu","District":"Krishnagiri","COORD_X":78.0996455457,"COORD_Y":12.4685557234}
{"State":"Tamil Nadu","District":"Erode","COORD_X":77.487740107,"COORD_Y":11.3992829993}
{"State":"Tamil Nadu","District":"Coimbatore","COORD_X":77.0200614517,"COORD_Y":10.9419270966}
{"State":"Telangana","District":"Warangal (R)","COORD_X":79.6714527381,"COORD_Y":18.0754356608}
{"State":"Mizoram","District":"Serchhip","COORD_X":92.9193410614,"COORD_Y":23.2439989561}
{"State":"Mizoram","District":"Aizawl","COORD_X":92.8801276945,"COORD_Y":23.8685094752}
{"State":"Maharashtra","District":"Mumbai Suburban","COORD_X":72.848272487,"COORD_Y":19.1381200907}
{"State":"Maharashtra","District":"Nagpur","COORD_X":79.0728252458,"COORD_Y":21.2150679222}
{"State":"Goa","District":"North Goa","COORD_X":73.8932256703,"COORD_Y":15.5245433045}
{"State":"Goa","District":"South Goa","COORD_X":73.9763817187,"COORD_Y":15.1679595597}
{"State":"Andaman & Nicobar Islands","District":"North  & Middle Andaman","COORD_X":92.8521211207,"COORD_Y":12.9083850075}
{"State":"Andaman & Nicobar Islands","District":"South Andaman","COORD_X":92.7122720513,"COORD_Y":11.6716380771}
{"State":"Andaman & Nicobar Islands","District":"Nicobars","COORD_X":93.5190292794,"COORD_Y":7.9645955404}
{"State":"Orissa","District":"Anugul","COORD_X":85.0108406917,"COORD_Y":21.0539437546}
{"State":"Puducherry","District":"Karaikal","COORD_X":79.821365418,"COORD_Y":10.9049677399}
{"State":"Puducherry","District":"Puducherry","COORD_X":79.7237910585,"COORD_Y":11.6506312875}
{"State":"Puducherry","District":"Mahe","COORD_X":75.5396681726,"COORD_Y":11.7241424365}
{"State":"Manipur","District":"Ukhrul","COORD_X":94.4223015267,"COORD_Y":25.14201994}
{"State":"Manipur","District":"Bishnupur","COORD_X":93.8224149947,"COORD_Y":24.5457056809}
{"State":"Manipur","District":"Churachandpur","COORD_X":93.4448867226,"COORD_Y":24.2826387677}
{"State":"Manipur","District":"Thoubal","COORD_X":93.9779375803,"COORD_Y":24.5523884222}
{"State":"Manipur","District":"Imphal East","COORD_X":93.97911792,"COORD_Y":24.8431373961}
{"State":"Manipur","District":"Senapati","COORD_X":94.0355907679,"COORD_Y":24.9523884902}
{"State":"Manipur","District":"Imphal West","COORD_X":93.8844812337,"COORD_Y":24.776740853}
{"State":"Nagaland","District":"Mon","COORD_X":95.0233547056,"COORD_Y":26.6133714358}
{"State":"Nagaland","District":"Tuensang","COORD_X":94.799406777,"COORD_Y":26.1793732696}
{"State":"Nagaland","District":"Mokokchung","COORD_X":94.5571956675,"COORD_Y":26.4198740098}
{"State":"Nagaland","District":"Longleng","COORD_X":94.8243126355,"COORD_Y":26.6133969996}
{"State":"Nagaland","District":"Phek","COORD_X":94.5515872915,"COORD_Y":25.6998959664}
{"State":"Assam","District":"Nalbari","COORD_X":91.3830675383,"COORD_Y":26.4122883157}
{"State":"Assam","District":"Dhubri","COORD_X":89.9866842901,"COORD_Y":26.0549857512}
{"State":"Assam","District":"Sivasagar","COORD_X":94.8727309504,"COORD_Y":27.0424118678}
{"State":"Assam","District":"Karimganj","COORD_X":92.3167806141,"COORD_Y":24.6896736648}
{"State":"Assam","District":"Tinsukia","COORD_X":95.6366847335,"COORD_Y":27.4805147257}
{"State":"Orissa","District":"Koraput","COORD_X":82.7663701988,"COORD_Y":18.8919068336}
{"State":"Assam","District":"Hailakandi","COORD_X":92.5894813742,"COORD_Y":24.5209463138}
{"State":"Orissa","District":"Nabarangapur","COORD_X":82.3893122943,"COORD_Y":19.4792755816}
{"State":"Orissa","District":"Bargarh","COORD_X":83.2744739141,"COORD_Y":21.1517502024}
{"State":"Assam","District":"Chirang","COORD_X":90.6687307308,"COORD_Y":26.5741668077}
{"State":"Assam","District":"Cachar","COORD_X":92.8083825025,"COORD_Y":24.8268483842}
{"State":"Assam","District":"Darrang","COORD_X":92.0642044983,"COORD_Y":26.4831220148}
{"State":"Assam","District":"Kamrup","COORD_X":91.4638815321,"COORD_Y":26.1598170785}
{"State":"Assam","District":"Dibrugarh","COORD_X":95.1234386919,"COORD_Y":27.2756991501}
{"State":"Assam","District":"Barpeta","COORD_X":90.998624439,"COORD_Y":26.3999270078}
{"State":"Orissa","District":"Balangir","COORD_X":83.2148290043,"COORD_Y":20.5869608696}
{"State":"Assam","District":"Dhemaji","COORD_X":94.5858327894,"COORD_Y":27.4868670011}
{"State":"Assam","District":"Sonitpur","COORD_X":92.8687546061,"COORD_Y":26.7470714711}
{"State":"Assam","District":"Udalguri","COORD_X":92.0895706676,"COORD_Y":26.661035483}
{"State":"Rajasthan","District":"Jhunjhunun","COORD_X":75.7492991617,"COORD_Y":28.1559190107}
{"State":"Rajasthan","District":"Jaisalmer","COORD_X":70.9521247709,"COORD_Y":27.3687815114}
{"State":"Rajasthan","District":"Sikar","COORD_X":75.3615517607,"COORD_Y":27.6624712912}
{"State":"Rajasthan","District":"Hanumangarh","COORD_X":74.8075211297,"COORD_Y":29.292136334}
{"State":"Rajasthan","District":"Nagaur","COORD_X":74.2778043319,"COORD_Y":27.0978163029}
{"State":"Rajasthan","District":"Barmer","COORD_X":71.382113808,"COORD_Y":25.6994662735}
{"State":"Rajasthan","District":"Ganganagar","COORD_X":73.5215357009,"COORD_Y":29.4081695043}
{"State":"Rajasthan","District":"Jodhpur","COORD_X":72.9302521577,"COORD_Y":26.6975734837}
{"State":"Rajasthan","District":"Churu","COORD_X":74.9432602683,"COORD_Y":28.4022134228}
{"State":"Rajasthan","District":"Bikaner","COORD_X":72.9982828323,"COORD_Y":28.2720669563}
{"State":"Rajasthan","District":"Pratapgarh (Rajasthan)","COORD_X":74.6891299737,"COORD_Y":24.0808451632}
{"State":"Assam","District":"Morigaon","COORD_X":92.3016058734,"COORD_Y":26.2761072532}
{"State":"Assam","District":"Karbi Anglong","COORD_X":93.0725881732,"COORD_Y":26.0707808535}
{"State":"Assam","District":"Lakhimpur","COORD_X":94.1462510367,"COORD_Y":27.164988302}
{"State":"Assam","District":"Golaghat","COORD_X":93.875021767,"COORD_Y":26.3765672791}
{"State":"Assam","District":"Dima Hasao","COORD_X":92.9619164118,"COORD_Y":25.3566003193}
{"State":"Rajasthan","District":"Pali","COORD_X":73.5476571202,"COORD_Y":25.7658691124}
{"State":"Rajasthan","District":"Rajsamand","COORD_X":74.0220508851,"COORD_Y":25.3242271507}
{"State":"Rajasthan","District":"Ajmer","COORD_X":74.7120717061,"COORD_Y":26.1727014736}
{"State":"Rajasthan","District":"Bharatpur","COORD_X":77.2035413372,"COORD_Y":27.4161789888}
{"State":"Rajasthan","District":"Dungarpur","COORD_X":73.8705136978,"COORD_Y":23.7658761245}
{"State":"Rajasthan","District":"Chittaurgarh","COORD_X":74.7971745111,"COORD_Y":24.8140443365}
{"State":"Rajasthan","District":"Udaipur","COORD_X":73.8184492382,"COORD_Y":24.4296594854}
{"State":"Rajasthan","District":"Jalor","COORD_X":72.2170582838,"COORD_Y":25.1179790332}
{"State":"Rajasthan","District":"Dausa","COORD_X":76.5529834107,"COORD_Y":26.884151878}
{"State":"Rajasthan","District":"Sirohi","COORD_X":72.7676023545,"COORD_Y":24.8223342681}
{"State":"Assam","District":"Bongaigaon","COORD_X":90.6215887923,"COORD_Y":26.3885704575}
{"State":"Meghalaya","District":"West Jaintia Hills","COORD_X":92.2098810624,"COORD_Y":25.3862600865}
{"State":"Tamil Nadu","District":"Sivaganga","COORD_X":78.5409671514,"COORD_Y":9.9629322505}
{"State":"Tamil Nadu","District":"Thanjavur","COORD_X":79.2887231109,"COORD_Y":10.7184761662}
{"State":"Tamil Nadu","District":"Tiruvannamalai","COORD_X":79.2634123978,"COORD_Y":12.4493312081}
{"State":"Assam","District":"Kamrup Metropolitan","COORD_X":91.7682880551,"COORD_Y":26.1085001865}
{"State":"Tamil Nadu","District":"Ramanathapuram","COORD_X":78.8596952161,"COORD_Y":9.4311987179}
{"State":"Tamil Nadu","District":"Tirunelveli","COORD_X":77.6192450635,"COORD_Y":8.7318750098}
{"State":"Tamil Nadu","District":"Virudhunagar","COORD_X":77.9574941165,"COORD_Y":9.5056106156}
{"State":"Assam","District":"Kokrajhar","COORD_X":90.1506012992,"COORD_Y":26.3976257273}
{"State":"Assam","District":"Jorhat","COORD_X":94.2458759757,"COORD_Y":26.7407345104}
{"State":"Tripura","District":"Khowai","COORD_X":91.6587964192,"COORD_Y":24.0613627862}
{"State":"Tripura","District":"Sipahijula","COORD_X":91.2808650895,"COORD_Y":23.5830064226}
{"State":"Meghalaya","District":"East Garo Hills","COORD_X":90.631637035,"COORD_Y":25.6688408536}
{"State":"Meghalaya","District":"North Garo Hills","COORD_X":90.6399846477,"COORD_Y":25.8747530885}
{"State":"Orissa","District":"Subarnapur","COORD_X":83.7548004541,"COORD_Y":20.9052199466}
{"State":"Orissa","District":"Puri","COORD_X":85.7204241723,"COORD_Y":19.9738870659}
{"State":"Orissa","District":"Debagarh","COORD_X":84.8482301868,"COORD_Y":21.3932218238}
{"State":"Meghalaya","District":"South West Garo Hills","COORD_X":89.9323482609,"COORD_Y":25.386434219}
{"State":"Meghalaya","District":"East Jaintia Hills","COORD_X":92.3952571544,"COORD_Y":25.2456140294}
{"State":"Orissa","District":"Jagatsinghapur","COORD_X":86.2729941928,"COORD_Y":20.2600552169}
{"State":"Orissa","District":"Kandhamal","COORD_X":84.0588792778,"COORD_Y":20.0639045556}
{"State":"Orissa","District":"Khordha","COORD_X":85.5803768716,"COORD_Y":20.1018264526}
{"State":"Orissa","District":"Mayurbhanj","COORD_X":86.4002806426,"COORD_Y":21.9191087048}
{"State":"Orissa","District":"Malkangiri","COORD_X":81.9866801818,"COORD_Y":18.2718156363}
{"State":"Orissa","District":"Baleshwar","COORD_X":86.9707095281,"COORD_Y":21.5741083699}
{"State":"Orissa","District":"Sambalpur","COORD_X":84.3258008278,"COORD_Y":21.5459935444}
{"State":"Orissa","District":"Gajapati","COORD_X":84.1737434567,"COORD_Y":19.1383765954}
{"State":"Orissa","District":"Dhenkanal","COORD_X":85.4854273631,"COORD_Y":20.8268791504}
{"State":"Orissa","District":"Nayagarh","COORD_X":85.06502565,"COORD_Y":20.2249540337}
{"State":"Orissa","District":"Cuttack","COORD_X":85.8050433996,"COORD_Y":20.4042071597}
{"State":"Orissa","District":"Jajapur","COORD_X":86.1477866136,"COORD_Y":20.8330821072}
{"State":"Orissa","District":"Kalahandi","COORD_X":83.1357463306,"COORD_Y":19.8486716694}
{"State":"Orissa","District":"Baudh","COORD_X":84.1540942538,"COORD_Y":20.6130551117}
{"State":"Orissa","District":"Kendrapara","COORD_X":86.5878421505,"COORD_Y":20.5268558589}
{"State":"Orissa","District":"Kendujhar","COORD_X":85.7515272487,"COORD_Y":21.5390713239}
{"State":"Orissa","District":"Ganjam","COORD_X":84.5343858723,"COORD_Y":19.5452464538}
{"State":"Orissa","District":"Sundargarh","COORD_X":84.5153091741,"COORD_Y":22.0942269048}
{"State":"Orissa","District":"Bhadrak","COORD_X":86.5648942256,"COORD_Y":21.0041575714}
{"State":"Orissa","District":"Nuapada","COORD_X":82.6078806361,"COORD_Y":20.5061717684}
{"State":"Orissa","District":"Rayagada","COORD_X":83.4711651659,"COORD_Y":19.3313097428}
{"State":"Orissa","District":"Jharsuguda","COORD_X":83.9429751124,"COORD_Y":21.8359397753}
{"State":"Chhatisgarh","District":"Bemetra","COORD_X":81.4644804146,"COORD_Y":21.6299897259}
{"State":"Chhatisgarh","District":"Bastar","COORD_X":81.8663535271,"COORD_Y":19.123722121}
{"State":"Tamil Nadu","District":"Thiruvarur","COORD_X":79.5144786836,"COORD_Y":10.7853557068}
{"State":"Tamil Nadu","District":"Thiruvallur","COORD_X":79.8955725955,"COORD_Y":13.1726796255}
{"State":"Chhatisgarh","District":"Mungeli","COORD_X":81.6356098506,"COORD_Y":22.2172200747}
{"State":"Chhatisgarh","District":"Bilaspur (Chhatisgarh)","COORD_X":82.0690879894,"COORD_Y":22.4963731773}
{"State":"Chhatisgarh","District":"Gariaband","COORD_X":82.3141237796,"COORD_Y":20.3204095392}
{"State":"Chhatisgarh","District":"Kabeerdham","COORD_X":81.1384766327,"COORD_Y":22.0654454252}
{"State":"Chhatisgarh","District":"Sukma","COORD_X":81.4473919029,"COORD_Y":18.3765867893}
{"State":"Chhatisgarh","District":"Uttar Bastar Kanker","COORD_X":81.036785466,"COORD_Y":20.1089140349}
{"State":"Chhatisgarh","District":"Baloda Bazar","COORD_X":82.2417674084,"COORD_Y":21.5328817732}
{"State":"Chhatisgarh","District":"Balod","COORD_X":81.2103723625,"COORD_Y":20.7726998378}
{"State":"Tamil Nadu","District":"Tiruchirappalli","COORD_X":78.5453605712,"COORD_Y":10.8238830007}
{"State":"Tamil Nadu","District":"Tiruppur","COORD_X":77.4241595689,"COORD_Y":10.9700398574}
{"State":"Tamil Nadu","District":"Madurai","COORD_X":78.0792480211,"COORD_Y":9.919386157}
{"State":"Tamil Nadu","District":"Karur","COORD_X":78.0936229059,"COORD_Y":10.8259782994}
{"State":"Tamil Nadu","District":"Dharmapuri","COORD_X":78.2078712636,"COORD_Y":12.1359211024}
{"State":"Tamil Nadu","District":"Namakkal","COORD_X":78.1228176595,"COORD_Y":11.36377018}
{"State":"Uttar Pradesh","District":"Moradabad","COORD_X":78.7855540526,"COORD_Y":28.9101588442}
{"State":"Uttar Pradesh","District":"Sambhal","COORD_X":78.6307682118,"COORD_Y":28.4549532699}
{"State":"Uttar Pradesh","District":"Budaun","COORD_X":78.9765922079,"COORD_Y":28.0950094636}
{"State":"Uttar Pradesh","District":"Kanshiram Nagar","COORD_X":78.8522919863,"COORD_Y":27.7456269901}
{"State":"Uttar Pradesh","District":"Bahraich","COORD_X":81.5975245664,"COORD_Y":27.6695586277}
{"State":"Uttar Pradesh","District":"Hapur","COORD_X":77.7712865836,"COORD_Y":28.7045944721}
{"State":"Uttar Pradesh","District":"Sitapur","COORD_X":80.8467492147,"COORD_Y":27.4951382251}
{"State":"Uttar Pradesh","District":"Samli","COORD_X":77.2503330921,"COORD_Y":29.4991860046}
{"State":"Chhatisgarh","District":"Dakshin Bastar Dantewada","COORD_X":81.4421975822,"COORD_Y":18.8239928917}
{"State":"Chhatisgarh","District":"Surguja","COORD_X":83.1454555008,"COORD_Y":23.0074704307}
{"State":"Chhatisgarh","District":"Balrampur (Chhatisgarh)","COORD_X":83.2686473251,"COORD_Y":23.6092902966}
{"State":"Chhatisgarh","District":"Kondagaon","COORD_X":81.6654934753,"COORD_Y":19.6939551789}
{"State":"Uttar Pradesh","District":"Shrawasti","COORD_X":81.8899471411,"COORD_Y":27.6645961071}
{"State":"Chhatisgarh","District":"Narayanpur","COORD_X":81.0911048633,"COORD_Y":19.5950970501}
{"State":"Chhatisgarh","District":"Durg","COORD_X":81.3902162069,"COORD_Y":21.2316341317}
{"State":"Chhatisgarh","District":"Surajpur","COORD_X":83.057074568,"COORD_Y":23.409730966}
{"State":"Chhatisgarh","District":"Bijapur (Chhatisgarh)","COORD_X":80.8640382603,"COORD_Y":18.8353098517}
{"State":"Uttar Pradesh","District":"Mathura","COORD_X":77.602440597,"COORD_Y":27.6293294279}
{"State":"Uttar Pradesh","District":"Etah","COORD_X":78.7279415867,"COORD_Y":27.5073498316}
{"State":"Uttar Pradesh","District":"Hardoi","COORD_X":80.255936307,"COORD_Y":27.3021310392}
{"State":"Uttar Pradesh","District":"Balrampur (Uttar Pradesh)","COORD_X":82.5336298355,"COORD_Y":27.526794296}
{"State":"Uttar Pradesh","District":"Mahamaya Nagar","COORD_X":78.1675360526,"COORD_Y":27.5808230609}
{"State":"Uttar Pradesh","District":"Shahjahanpur","COORD_X":79.8322803202,"COORD_Y":27.9595544022}
{"State":"Uttar Pradesh","District":"Farrukhabad","COORD_X":79.4465566304,"COORD_Y":27.4341235404}
{"State":"Uttar Pradesh","District":"Kannauj","COORD_X":79.6538391899,"COORD_Y":27.0195373955}
{"State":"Uttar Pradesh","District":"Pilibhit","COORD_X":79.9163251942,"COORD_Y":28.622093443}
{"State":"Uttar Pradesh","District":"Mainpuri","COORD_X":79.0859654509,"COORD_Y":27.1956315942}
{"State":"Uttar Pradesh","District":"Jyotiba Phule Nagar","COORD_X":78.3544048681,"COORD_Y":28.8040619292}
{"State":"Chhatisgarh","District":"Raipur","COORD_X":81.7896149118,"COORD_Y":21.3009355686}
{"State":"Chhatisgarh","District":"Koriya","COORD_X":82.019192407,"COORD_Y":23.5498673559}
{"State":"Chhatisgarh","District":"Dhamtari","COORD_X":81.7433973111,"COORD_Y":20.5749545585}
{"State":"Chhatisgarh","District":"Korba","COORD_X":82.5767117046,"COORD_Y":22.493196575}
{"State":"Chhatisgarh","District":"Raigarh (Chhatisgarh)","COORD_X":83.3064751197,"COORD_Y":21.9719496246}
{"State":"Chhatisgarh","District":"Jashpur","COORD_X":83.8899098395,"COORD_Y":22.7906766239}
{"State":"Chhatisgarh","District":"Mahasamund","COORD_X":82.6868508102,"COORD_Y":21.2159042443}
{"State":"Chhatisgarh","District":"Rajnandgaon","COORD_X":80.7971169597,"COORD_Y":21.0360059919}
{"State":"Chhatisgarh","District":"Janjgir-Champa","COORD_X":82.8021493965,"COORD_Y":21.9444799713}
{"State":"Rajasthan","District":"Bhilwara","COORD_X":74.7135227695,"COORD_Y":25.4549774863}
{"State":"Rajasthan","District":"Tonk","COORD_X":75.757460156,"COORD_Y":26.1029369639}
{"State":"Rajasthan","District":"Bundi","COORD_X":75.8358720333,"COORD_Y":25.4794098213}
{"State":"Rajasthan","District":"Jaipur","COORD_X":75.8296174157,"COORD_Y":27.1163636381}
{"State":"Rajasthan","District":"Kota","COORD_X":76.178867836,"COORD_Y":25.1490074624}
{"State":"Tamil Nadu","District":"Ariyalur","COORD_X":79.2311402477,"COORD_Y":11.1775518275}
{"State":"Tamil Nadu","District":"Theni","COORD_X":77.4741222508,"COORD_Y":9.9637501336}
{"State":"Tamil Nadu","District":"Salem","COORD_X":78.2001694996,"COORD_Y":11.6421041508}
{"State":"Uttar Pradesh","District":"Firozabad","COORD_X":78.5174791199,"COORD_Y":27.1814840743}
{"State":"Uttar Pradesh","District":"Sultanpur","COORD_X":82.2388419507,"COORD_Y":26.2411322476}
{"State":"Uttar Pradesh","District":"Chitrakoot","COORD_X":81.1350722958,"COORD_Y":25.118603477}
{"State":"Uttar Pradesh","District":"Basti","COORD_X":82.7058827097,"COORD_Y":26.8460121075}
{"State":"Uttar Pradesh","District":"Gorakhpur","COORD_X":83.3493314659,"COORD_Y":26.6871859832}
{"State":"Uttar Pradesh","District":"Lucknow","COORD_X":80.9017887919,"COORD_Y":26.842219494}
{"State":"Uttar Pradesh","District":"Azamgarh","COORD_X":83.1121519847,"COORD_Y":26.0165848201}
{"State":"Uttar Pradesh","District":"Faizabad","COORD_X":81.9550125345,"COORD_Y":26.6344702162}
{"State":"Tamil Nadu","District":"Perambalur","COORD_X":78.8994533929,"COORD_Y":11.2853169941}
{"State":"Tamil Nadu","District":"Dindigul","COORD_X":77.8320574787,"COORD_Y":10.4136115164}
{"State":"Uttar Pradesh","District":"Meerut","COORD_X":77.7820280654,"COORD_Y":29.0029563896}
{"State":"Uttar Pradesh","District":"Aligarh","COORD_X":77.974019635,"COORD_Y":27.9095369666}
{"State":"Uttar Pradesh","District":"Bulandshahr","COORD_X":77.9589634448,"COORD_Y":28.3375857698}
{"State":"Uttar Pradesh","District":"Bijnor","COORD_X":78.488586529,"COORD_Y":29.4411313926}
{"State":"Uttar Pradesh","District":"Baghpat","COORD_X":77.2727722013,"COORD_Y":29.0212205358}
{"State":"Uttar Pradesh","District":"Kheri","COORD_X":80.6464492744,"COORD_Y":28.2073903368}
{"State":"Uttar Pradesh","District":"Rampur","COORD_X":79.2170225672,"COORD_Y":28.9373744826}
{"State":"Uttar Pradesh","District":"Bareilly","COORD_X":79.4449884927,"COORD_Y":28.5240930055}
{"State":"Uttar Pradesh","District":"Kaushambi","COORD_X":81.4419699824,"COORD_Y":25.5105061633}
{"State":"Uttar Pradesh","District":"Jalaun","COORD_X":79.3756095465,"COORD_Y":26.082247907}
{"State":"Uttar Pradesh","District":"Auraiya","COORD_X":79.4772064069,"COORD_Y":26.6643236597}
{"State":"Uttar Pradesh","District":"Pratapgarh (Uttar Pradesh)","COORD_X":81.8969025529,"COORD_Y":25.8715597696}
{"State":"Uttar Pradesh","District":"Hamirpur (Uttar Pradesh)","COORD_X":79.8658579442,"COORD_Y":25.7623073476}
{"State":"Uttar Pradesh","District":"Gonda","COORD_X":82.0788784171,"COORD_Y":27.119369509}
{"State":"Uttar Pradesh","District":"Kanpur Dehat","COORD_X":79.9191588737,"COORD_Y":26.4383666925}
{"State":"Uttar Pradesh","District":"Jaunpur","COORD_X":82.5855961438,"COORD_Y":25.733744084}
{"State":"Tamil Nadu","District":"Chennai","COORD_X":80.2311222151,"COORD_Y":13.0622329393}
{"State":"Tamil Nadu","District":"Nagapattinam","COORD_X":79.7080977915,"COORD_Y":10.9128215058}
{"State":"Tamil Nadu","District":"Viluppuram","COORD_X":79.4151195952,"COORD_Y":11.9587832771}
{"State":"Tamil Nadu","District":"Kancheepuram","COORD_X":79.9369150842,"COORD_Y":12.8200363938}
{"State":"Rajasthan","District":"Banswara","COORD_X":74.4285830986,"COORD_Y":23.4825695227}
{"State":"Tamil Nadu","District":"Kanniyakumari","COORD_X":77.4304692245,"COORD_Y":8.2583151939}
{"State":"Tamil Nadu","District":"Thoothukkudi","COORD_X":77.950201476,"COORD_Y":8.9172939237}
{"State":"Uttar Pradesh","District":"Allahabad","COORD_X":81.9234516965,"COORD_Y":25.297712981}
{"State":"Tamil Nadu","District":"The Nilgiris","COORD_X":76.6586921392,"COORD_Y":11.4667181443}
{"State":"Rajasthan","District":"Jhalawar","COORD_X":76.1512625876,"COORD_Y":24.2958357062}
{"State":"Rajasthan","District":"Alwar","COORD_X":76.6432957618,"COORD_Y":27.7760280921}
{"State":"Rajasthan","District":"Baran","COORD_X":76.7540793186,"COORD_Y":24.9409133372}
{"State":"Rajasthan","District":"Karauli","COORD_X":76.9589820309,"COORD_Y":26.5471809884}
{"State":"Rajasthan","District":"Dhaulpur","COORD_X":77.7720024663,"COORD_Y":26.7231973886}
{"State":"Rajasthan","District":"Sawai Madhopur","COORD_X":76.4338425031,"COORD_Y":26.229735289}
{"State":"Telangana","District":"Jangaon","COORD_X":79.2511202507,"COORD_Y":17.7758331527}
{"State":"Telangana","District":"Mancherial","COORD_X":79.5337529782,"COORD_Y":18.8975859802}
{"State":"Telangana","District":"Bhadradri","COORD_X":81.0968246689,"COORD_Y":17.7994656945}
{"State":"Telangana","District":"Hydrabad","COORD_X":78.4795101948,"COORD_Y":17.4172304897}
{"State":"Telangana","District":"Karimnagar","COORD_X":79.4044051601,"COORD_Y":18.3670456949}
{"State":"Telangana","District":"Nizamabad","COORD_X":78.1841293022,"COORD_Y":18.7810683581}
{"State":"Telangana","District":"Medak","COORD_X":78.2964508797,"COORD_Y":18.0641344962}
{"State":"Telangana","District":"Rangareddy","COORD_X":78.4399948854,"COORD_Y":17.3087858077}
{"State":"Telangana","District":"Nalgonda","COORD_X":78.9730832588,"COORD_Y":16.6992280458}
{"State":"Telangana","District":"Nagarkurnool","COORD_X":78.7345999669,"COORD_Y":16.35085761}
{"State":"Telangana","District":"Adilabad","COORD_X":78.5411443429,"COORD_Y":19.6948905688}
{"State":"Telangana","District":"Komaram Bheem","COORD_X":79.5463871535,"COORD_Y":19.4756263233}
{"State":"Telangana","District":"Nirmal","COORD_X":78.1612776509,"COORD_Y":19.0656611617}
{"State":"Telangana","District":"Jagtial","COORD_X":78.870797278,"COORD_Y":18.9242608255}
{"State":"Telangana","District":"Kamareddy","COORD_X":77.9997066888,"COORD_Y":18.2787327825}
{"State":"Telangana","District":"Warangal (U)","COORD_X":79.495518728,"COORD_Y":18.0914553876}
{"State":"Telangana","District":"Jayashankar","COORD_X":80.224200999,"COORD_Y":18.5072372274}
{"State":"Telangana","District":"Peddapalli","COORD_X":79.5268416541,"COORD_Y":18.7356494646}
{"State":"Telangana","District":"Rajanna Sircilla","COORD_X":78.6587227393,"COORD_Y":18.3596332722}
{"State":"Telangana","District":"Sangareddy","COORD_X":77.8795418441,"COORD_Y":17.7471108659}
{"State":"Telangana","District":"Siddipet","COORD_X":78.7512624119,"COORD_Y":17.962828486}
{"State":"Telangana","District":"Mahabubabad","COORD_X":79.9290447772,"COORD_Y":17.4857871881}
{"State":"Telangana","District":"Khammam","COORD_X":80.3221345877,"COORD_Y":17.0882394885}
{"State":"Telangana","District":"Suryapet","COORD_X":79.8496254833,"COORD_Y":17.0968835277}
{"State":"Telangana","District":"Jogulamba","COORD_X":77.7335037148,"COORD_Y":16.01001823}
{"State":"Telangana","District":"Yadadri","COORD_X":78.9001798949,"COORD_Y":17.4848544158}
{"State":"Telangana","District":"Medchal","COORD_X":78.5225243364,"COORD_Y":17.5061404704}
{"State":"Telangana","District":"Wanaparthy","COORD_X":78.1137485147,"COORD_Y":16.1928889018}
{"State":"Telangana","District":"Vikarabad","COORD_X":77.6908605721,"COORD_Y":17.2964387676}
{"State":"Telangana","District":"Mahabubnagar","COORD_X":77.4824742877,"COORD_Y":16.5918113347}
{"State":"Ladakh","District":"Kargil","COORD_X":76.287987136,"COORD_Y":33.9795706393}
{"State":"Ladakh","District":"Leh (Ladakh)","COORD_X":78.3359008749,"COORD_Y":34.0703730961}